dx/__init__.py
dx/dx.py
dx/filtering.py
dx/loggers.py
dx/sampling.py
dx/settings.py
dx/comms/__init__.py
dx/comms/assignment.py
dx/comms/rename.py
dx/comms/resample.py
dx/datatypes/__init__.py
dx/datatypes/compatibility.py
dx/datatypes/date_time.py
dx/datatypes/geometry.py
dx/datatypes/main.py
dx/datatypes/misc.py
dx/datatypes/numeric.py
dx/datatypes/text.py
dx/formatters/__init__.py
dx/formatters/enhanced.py
dx/formatters/main.py
dx/formatters/plain.py
dx/formatters/simple.py
dx/plotting/__init__.py
dx/plotting/dashboards.py
dx/plotting/main.py
dx/plotting/dex/__init__.py
dx/plotting/dex/_samples.py
dx/plotting/dex/basic.py
dx/plotting/dex/comparison.py
dx/plotting/dex/funnel.py
dx/plotting/dex/maps.py
dx/plotting/dex/part_to_whole.py
dx/plotting/dex/relationship.py
dx/plotting/dex/summary.py
dx/plotting/dex/time_series.py
dx/types/__init__.py
dx/types/dex_metadata.py
dx/types/filters.py
dx/types/main.py
dx/types/charts/__init__.py
dx/types/charts/_base.py
dx/types/charts/bar.py
dx/types/charts/line.py
dx/types/charts/options.py
dx/types/charts/parcoords.py
dx/types/charts/pie.py
dx/types/charts/scatter.py
dx/types/charts/summary.py
dx/types/charts/tilemap.py
dx/types/charts/violin.py
dx/types/charts/wordcloud.py
dx/utils/__init__.py
dx/utils/formatting.py
dx/utils/tracking.py
elixir_dx-1.0.0.dist-info/LICENSE.md
elixir_dx-1.0.0.dist-info/METADATA
elixir_dx-1.0.0.dist-info/WHEEL
elixir_dx-1.0.0.dist-info/top_level.txt
elixir_dx-1.0.0.dist-info/RECORD
