Metadata-Version: 2.1
Name: elixir-dx
Version: 1.0.0
Summary: Python wrapper for Data Explorer
Author-email: ciusji <bqjimaster@gmail.com>
Keywords: data,exploration,visualization
License-File: LICENSE.md
Requires-Dist: pandas (>=1.3.5)
Requires-Dist: ipython (>=7.31.1)
Requires-Dist: pydantic (>=1.9)
Requires-Dist: structlog (>=22.1.0)
Requires-Dist: duckdb (>=0.6.1)
